[
  {
    "url": "www.telerc.travail.gouv.fr",
    "result": {
      "host": "www.telerc.travail.gouv.fr",
      "port": 443,
      "protocol": "http",
      "isPublic": false,
      "status": "IN_PROGRESS",
      "startTime": 1616622038666,
      "engineVersion": "2.1.8",
      "criteriaVersion": "2009q",
      "endpoints": [
        {
          "ipAddress": "164.131.132.45",
          "statusMessage": "In progress",
          "statusDetails": "TESTING_BLEICHENBACHER",
          "statusDetailsMessage": "Testing Bleichenbacher",
          "progress": 90,
          "eta": 15,
          "delegation": 2
        }
      ]
    }
  },
  {
    "url": "election-tpe.travail.gouv.fr",
    "result": {
      "host": "election-tpe.travail.gouv.fr",
      "port": 443,
      "protocol": "http",
      "isPublic": true,
      "status": "READY",
      "startTime": 1616596556438,
      "testTime": 1616596638244,
      "engineVersion": "2.1.8",
      "criteriaVersion": "2009q",
      "endpoints": [
        {
          "ipAddress": "194.5.115.249",
          "statusMessage": "Ready",
          "grade": "A+",
          "gradeTrustIgnored": "A+",
          "hasWarnings": false,
          "isExceptional": true,
          "progress": 100,
          "duration": 80637,
          "eta": 1217,
          "delegation": 1
        }
      ]
    }
  },
  {
    "url": "www.teleaccords.travail-emploi.gouv.fr",
    "result": {
      "host": "www.teleaccords.travail-emploi.gouv.fr",
      "port": 443,
      "protocol": "http",
      "isPublic": false,
      "status": "IN_PROGRESS",
      "startTime": 1616622211161,
      "engineVersion": "2.1.8",
      "criteriaVersion": "2009q",
      "endpoints": [
        {
          "ipAddress": "164.131.132.47",
          "statusMessage": "In progress",
          "statusDetails": "TESTING_HANDSHAKE_SIMULATION",
          "statusDetailsMessage": "Simulating handshakes",
          "progress": 97,
          "eta": 4,
          "delegation": 2
        }
      ]
    }
  },
  {
    "url": "www.sipsi.travail.gouv.fr",
    "result": {
      "host": "www.sipsi.travail.gouv.fr",
      "port": 443,
      "protocol": "http",
      "isPublic": false,
      "status": "READY",
      "startTime": 1616622414283,
      "testTime": 1616622585809,
      "engineVersion": "2.1.8",
      "criteriaVersion": "2009q",
      "endpoints": [
        {
          "ipAddress": "164.131.131.49",
          "serverName": "www.sipsi.travail.gouv.fr",
          "statusMessage": "Ready",
          "grade": "B",
          "gradeTrustIgnored": "B",
          "hasWarnings": true,
          "isExceptional": false,
          "progress": 100,
          "duration": 170963,
          "eta": 0,
          "delegation": 2
        }
      ]
    }
  }
]
